{
    "AppID": 2236250,
    "Name": "Smelogs Playground Playtest",
    "Release date": "Dec 7, 2022",
    "About the game": NaN,
    "Header image": "https://cdn.akamai.steamstatic.com/steam/apps/2236250/header.jpg?t=1670436087",
    "Price": 0.0,
    "Developers": NaN,
    "Publishers": NaN,
    "Screenshots": NaN,
    "Slug": "smelogs-playground-playtest",
    "Meta Title": "Smelogs Playground Playtest: Dec 7, 2022, nan and Full Ov...",
    "Meta Description": "Looking for information on Smelogs Playground Playtest? Check out the release date (Dec 7, 2022), developer insights from nan, and a complete game summary.",
    "Alt Text Image": "Official header image for Smelogs Playground Playtest game - Steam 2236250",
    "Canonical URL": "https://gusku.site/game/smelogs-playground-playtest",
    "Schema JSON-LD": "{\"@context\": \"https://schema.org\", \"@type\": \"VideoGame\", \"name\": \"Smelogs Playground Playtest\", \"description\": \"Looking for information on Smelogs Playground Playtest? Check out the release date (Dec 7, 2022), developer insights from nan, and a complete game summary.\", \"applicationCategory\": \"Game\", \"operatingSystem\": \"Windows, macOS, Linux\", \"datePublished\": \"Dec 7, 2022\", \"author\": {\"@type\": \"Organization\", \"name\": NaN}, \"publisher\": {\"@type\": \"Organization\", \"name\": NaN}, \"image\": \"https://cdn.akamai.steamstatic.com/steam/apps/2236250/header.jpg?t=1670436087\", \"offers\": {\"@type\": \"Offer\", \"price\": 0.0, \"priceCurrency\": \"USD\"}}",
    "img_width": 600,
    "img_height": 900,
    "Link Monetag": "https://otieu.com/4/8764643",
    "Link Adsterra": "https://www.effectivegatecpm.com/xjsgcgii37?key=606d2c74ae50bd149743d90c3719a164"
}