{
    "AppID": 1414700,
    "Name": "The Imagined Leviathan: Prologue",
    "Release date": "Sep 23, 2020",
    "About the game": "We are developing this short experience into a new full game called Imagined Leviathans, which will greatly develop the gameplay and themes into a full 2-3 hours of play, with improved visuals and significantly more to do and see, including meeting other survivors “At fifty degrees below zero frostbite can strike in as few as five minutes” A poetic survival horror set in a future where climate change has rendered Britain an arctic wasteland. On your pilgrimage to Steel Henge you can only take what you can carry, so choose carefully what you leave behind. Immerse yourself in this starkly monochromatic world as you scavenge for fuel, take shelter in the shadows, and burn stories to stay warm. A malevolent presence lurks between the words, just out of reach. Alone, you must sacrifice everything you knew to deliver the bitter truth of this world to future generations. A brief but intense 20 minutes.",
    "Header image": "https://cdn.akamai.steamstatic.com/steam/apps/1414700/header.jpg?t=1623880189",
    "Price": 0.0,
    "Developers": "Chard,de Fault,Richard Campbell",
    "Publishers": "Far Few Giants",
    "Screenshots": "https://cdn.akamai.steamstatic.com/steam/apps/1414700/ss_b7e0b704c37cca7d51ef284e654830826f8704a2.1920x1080.jpg?t=1623880189,https://cdn.akamai.steamstatic.com/steam/apps/1414700/ss_ece7668889cc854620b532f1c63c78e11e45c955.1920x1080.jpg?t=1623880189,https://cdn.akamai.steamstatic.com/steam/apps/1414700/ss_d0585e7582597cfa15a0000c8efea077451616db.1920x1080.jpg?t=1623880189,https://cdn.akamai.steamstatic.com/steam/apps/1414700/ss_97c29991c3756065b39adeab38983274e3d0a226.1920x1080.jpg?t=1623880189,https://cdn.akamai.steamstatic.com/steam/apps/1414700/ss_57738e2bee3504a8c74babd5e9c51f7fba8f569d.1920x1080.jpg?t=1623880189,https://cdn.akamai.steamstatic.com/steam/apps/1414700/ss_68c54bcdb5d864192a829bd589338235a77b4160.1920x1080.jpg?t=1623880189,https://cdn.akamai.steamstatic.com/steam/apps/1414700/ss_6d0647a99932dd404311a117e06deaf3b1996809.1920x1080.jpg?t=1623880189,https://cdn.akamai.steamstatic.com/steam/apps/1414700/ss_2d31871ea4fc6aea880868d8f8e77fc2d6b95719.1920x1080.jpg?t=1623880189,https://cdn.akamai.steamstatic.com/steam/apps/1414700/ss_25da3602c8868126879c54a3fbbb39f138ddd403.1920x1080.jpg?t=1623880189,https://cdn.akamai.steamstatic.com/steam/apps/1414700/ss_b7c415752daf58e000131c9bfa47e2dc5f974d4e.1920x1080.jpg?t=1623880189,https://cdn.akamai.steamstatic.com/steam/apps/1414700/ss_de5d34bbec375d2899f53fc8f0b6f2f6e99a00b7.1920x1080.jpg?t=1623880189,https://cdn.akamai.steamstatic.com/steam/apps/1414700/ss_fbc36146163f9d6848b8dd64fb0576a8ab526db3.1920x1080.jpg?t=1623880189,https://cdn.akamai.steamstatic.com/steam/apps/1414700/ss_9ab53cce07092dc4ffbbd62c3bba5e2b50b3697d.1920x1080.jpg?t=1623880189,https://cdn.akamai.steamstatic.com/steam/apps/1414700/ss_25da3602c8868126879c54a3fbbb39f138ddd403.1920x1080.jpg?t=1623880189,https://cdn.akamai.steamstatic.com/steam/apps/1414700/ss_4cfb794c0f971e5c624b9300e82db1781bbf2a15.1920x1080.jpg?t=1623880189,https://cdn.akamai.steamstatic.com/steam/apps/1414700/ss_c58a0f14e87fd5228bd9eeea3e0feb1680d32e7f.1920x1080.jpg?t=1623880189",
    "Slug": "the-imagined-leviathan-prologue",
    "Meta Title": "The Imagined Leviathan: Prologue: Sep 23, 2020, Chard,de ...",
    "Meta Description": "Looking for information on The Imagined Leviathan: Prologue? Check out the release date (Sep 23, 2020), developer insights from Chard,de Fault,Richard C...",
    "Alt Text Image": "Official header image for The Imagined Leviathan: Prologue game - Steam 1414700",
    "Canonical URL": "https://gusku.site/game/the-imagined-leviathan-prologue",
    "Schema JSON-LD": "{\"@context\": \"https://schema.org\", \"@type\": \"VideoGame\", \"name\": \"The Imagined Leviathan: Prologue\", \"description\": \"Looking for information on The Imagined Leviathan: Prologue? Check out the release date (Sep 23, 2020), developer insights from Chard,de Fault,Richard C...\", \"applicationCategory\": \"Game\", \"operatingSystem\": \"Windows, macOS, Linux\", \"datePublished\": \"Sep 23, 2020\", \"author\": {\"@type\": \"Organization\", \"name\": \"Chard,de Fault,Richard Campbell\"}, \"publisher\": {\"@type\": \"Organization\", \"name\": \"Far Few Giants\"}, \"image\": \"https://cdn.akamai.steamstatic.com/steam/apps/1414700/header.jpg?t=1623880189\", \"offers\": {\"@type\": \"Offer\", \"price\": 0.0, \"priceCurrency\": \"USD\"}}",
    "img_width": 600,
    "img_height": 900,
    "Link Monetag": "https://otieu.com/4/8764643",
    "Link Adsterra": "https://www.effectivegatecpm.com/xjsgcgii37?key=606d2c74ae50bd149743d90c3719a164"
}