{
    "AppID": 383580,
    "Name": "Flesh Eaters",
    "Release date": "May 3, 2016",
    "About the game": "Flesh Eaters is retro style single player RTS zombie survival game with resource gathering and crafting. Zombies are everywhere! You must gather resources to build barricades, upgrade weapons and armour and explore the city under the siege of the dead Features: ★ Equip and upgrade different weapons and armour for your survivors. ★ Level up and upgrade your survivors stats ★ Gather resources to build barricades and defend your survivors against the horde. ★ Fight against different types of zombies ★ 3 different survivor classes to chose from, each class has 3 unique skills. Solider - The soldier can equip weapons and armours. Medic - The medic can heal other survivors and equip melee weapons. Engineer - The engineer can build turrets, traps and equip melee weapons.",
    "Header image": "https://cdn.akamai.steamstatic.com/steam/apps/383580/header.jpg?t=1576905019",
    "Price": 1.99,
    "Developers": "S.C. 16 BIT NIGHTS S.R.L.",
    "Publishers": "S.C. 16 BIT NIGHTS S.R.L.",
    "Screenshots": "https://cdn.akamai.steamstatic.com/steam/apps/383580/ss_80ee3fe64d1f9c73c17d71a5334da9de3b82e5b0.1920x1080.jpg?t=1576905019,https://cdn.akamai.steamstatic.com/steam/apps/383580/ss_49f7064415d15b9729a8d51701c156bd3b515a31.1920x1080.jpg?t=1576905019,https://cdn.akamai.steamstatic.com/steam/apps/383580/ss_0ab4356d651f4b5c027b0e9f624a547740a0de07.1920x1080.jpg?t=1576905019,https://cdn.akamai.steamstatic.com/steam/apps/383580/ss_50bab26ee30d6540c52d1210d1f6c46919ffda82.1920x1080.jpg?t=1576905019,https://cdn.akamai.steamstatic.com/steam/apps/383580/ss_62048e5d422137bb9839f0e917dcdfb50b96baf8.1920x1080.jpg?t=1576905019",
    "Slug": "flesh-eaters",
    "Meta Title": "Flesh Eaters: May 3, 2016, S.C. 16 BIT NIGHTS S.R.L. and ...",
    "Meta Description": "Looking for information on Flesh Eaters? Check out the release date (May 3, 2016), developer insights from S.C. 16 BIT NIGHTS S.R.L., and a complete gam...",
    "Alt Text Image": "Official header image for Flesh Eaters game - Steam 383580",
    "Canonical URL": "https://gusku.site/game/flesh-eaters",
    "Schema JSON-LD": "{\"@context\": \"https://schema.org\", \"@type\": \"VideoGame\", \"name\": \"Flesh Eaters\", \"description\": \"Looking for information on Flesh Eaters? Check out the release date (May 3, 2016), developer insights from S.C. 16 BIT NIGHTS S.R.L., and a complete gam...\", \"applicationCategory\": \"Game\", \"operatingSystem\": \"Windows, macOS, Linux\", \"datePublished\": \"May 3, 2016\", \"author\": {\"@type\": \"Organization\", \"name\": \"S.C. 16 BIT NIGHTS S.R.L.\"}, \"publisher\": {\"@type\": \"Organization\", \"name\": \"S.C. 16 BIT NIGHTS S.R.L.\"}, \"image\": \"https://cdn.akamai.steamstatic.com/steam/apps/383580/header.jpg?t=1576905019\", \"offers\": {\"@type\": \"Offer\", \"price\": 1.99, \"priceCurrency\": \"USD\"}}",
    "img_width": 600,
    "img_height": 900,
    "Link Monetag": "https://otieu.com/4/8764643",
    "Link Adsterra": "https://www.effectivegatecpm.com/xjsgcgii37?key=606d2c74ae50bd149743d90c3719a164"
}