{
    "AppID": 878240,
    "Name": "Adva-lines",
    "Release date": "Jul 27, 2018",
    "About the game": "KEY FEATURES: 15+ mission types with rich mechanics. 3 pvp hotseat 2 player modes. Campaign of 100+ hours of solid gameplay that functuionally binds all the mission types together. Functional achievements (they give you ingame bonuses) 1.5+ hours OST What this game offers to you is: CLASSIC LINES expirience with additional Perks mechanic Many alternative, more complex, even hardcore modes based on a match-5 basis Awakening Art VIP VIRUS SIGNAL ...weaved with puzzles... Mechanico Memory ...weaved with strategy and base building elements... Excavation ...Arcade modes with rich upgrade systems... Rupture Starfall ...2-Players PVP modes... Kingdoms Brawl Borders Rush ...80+ hours Campaigns with difficulty progression...",
    "Header image": "https://cdn.akamai.steamstatic.com/steam/apps/878240/header.jpg?t=1655114829",
    "Price": 6.99,
    "Developers": "Mindfog games",
    "Publishers": "Mindfog games",
    "Screenshots": "https://cdn.akamai.steamstatic.com/steam/apps/878240/ss_82d3a1065c29b4e50bf1b01014878abc8cb40f90.1920x1080.jpg?t=1655114829,https://cdn.akamai.steamstatic.com/steam/apps/878240/ss_6ada987bbee9d5c7a0eb4d576152813b3117c9d1.1920x1080.jpg?t=1655114829,https://cdn.akamai.steamstatic.com/steam/apps/878240/ss_98f70a8faa95cd7175529556caa1359084b2cb6c.1920x1080.jpg?t=1655114829,https://cdn.akamai.steamstatic.com/steam/apps/878240/ss_b711a6f50457d66297d8ae0711f7a04ad298dc0e.1920x1080.jpg?t=1655114829,https://cdn.akamai.steamstatic.com/steam/apps/878240/ss_e4b503fdd5f6e1ed30a6e948070ac38ce14f4c9e.1920x1080.jpg?t=1655114829,https://cdn.akamai.steamstatic.com/steam/apps/878240/ss_cd782283410d7c44aba35f457e94ad8410e8d75e.1920x1080.jpg?t=1655114829,https://cdn.akamai.steamstatic.com/steam/apps/878240/ss_9f87fad8d1c61c606581d073812498cfa4489140.1920x1080.jpg?t=1655114829,https://cdn.akamai.steamstatic.com/steam/apps/878240/ss_5de9d280552944a2c86ea47df1f6c40a8121689b.1920x1080.jpg?t=1655114829,https://cdn.akamai.steamstatic.com/steam/apps/878240/ss_dea862b595200647bd32d94b36115966ee1e0abb.1920x1080.jpg?t=1655114829,https://cdn.akamai.steamstatic.com/steam/apps/878240/ss_9b0f4e66bbf8f0f4fbabbbb64e7511244024b8d5.1920x1080.jpg?t=1655114829,https://cdn.akamai.steamstatic.com/steam/apps/878240/ss_baa40c5dc7cd2a9f90558ddce0cf9fa052c24f7a.1920x1080.jpg?t=1655114829,https://cdn.akamai.steamstatic.com/steam/apps/878240/ss_1f9b6f6d42855a8b29a0f7d54067c762ab4a63d8.1920x1080.jpg?t=1655114829,https://cdn.akamai.steamstatic.com/steam/apps/878240/ss_c967e39f5afe6c84a3073946c53ce52ee1454bf0.1920x1080.jpg?t=1655114829,https://cdn.akamai.steamstatic.com/steam/apps/878240/ss_7b9e25b170f36922cafefa2ad5209eb499f3659c.1920x1080.jpg?t=1655114829,https://cdn.akamai.steamstatic.com/steam/apps/878240/ss_f50ed21e149ad316f92a359be3aa83dd25c50627.1920x1080.jpg?t=1655114829,https://cdn.akamai.steamstatic.com/steam/apps/878240/ss_596544b08c9a9649a36265c0230e427fd23d5d29.1920x1080.jpg?t=1655114829,https://cdn.akamai.steamstatic.com/steam/apps/878240/ss_72fcea5048b6db635561c9f20158da0755397d54.1920x1080.jpg?t=1655114829,https://cdn.akamai.steamstatic.com/steam/apps/878240/ss_160e0429ad1c6749b13f9a83c4e77d5f8e0d359d.1920x1080.jpg?t=1655114829,https://cdn.akamai.steamstatic.com/steam/apps/878240/ss_8bd8ab290feb8f88c5d556a4e644643f23b20c99.1920x1080.jpg?t=1655114829,https://cdn.akamai.steamstatic.com/steam/apps/878240/ss_35cdda90f50fa49009519d7bfa76be15e5bfcf7e.1920x1080.jpg?t=1655114829",
    "Slug": "adva-lines",
    "Meta Title": "Adva-lines: Jul 27, 2018, Mindfog games and Full Overview",
    "Meta Description": "Looking for information on Adva-lines? Check out the release date (Jul 27, 2018), developer insights from Mindfog games, and a complete game summary.",
    "Alt Text Image": "Official header image for Adva-lines game - Steam 878240",
    "Canonical URL": "https://gusku.site/game/adva-lines",
    "Schema JSON-LD": "{\"@context\": \"https://schema.org\", \"@type\": \"VideoGame\", \"name\": \"Adva-lines\", \"description\": \"Looking for information on Adva-lines? Check out the release date (Jul 27, 2018), developer insights from Mindfog games, and a complete game summary.\", \"applicationCategory\": \"Game\", \"operatingSystem\": \"Windows, macOS, Linux\", \"datePublished\": \"Jul 27, 2018\", \"author\": {\"@type\": \"Organization\", \"name\": \"Mindfog games\"}, \"publisher\": {\"@type\": \"Organization\", \"name\": \"Mindfog games\"}, \"image\": \"https://cdn.akamai.steamstatic.com/steam/apps/878240/header.jpg?t=1655114829\", \"offers\": {\"@type\": \"Offer\", \"price\": 6.99, \"priceCurrency\": \"USD\"}}",
    "img_width": 600,
    "img_height": 900,
    "Link Monetag": "https://otieu.com/4/8764643",
    "Link Adsterra": "https://www.effectivegatecpm.com/xjsgcgii37?key=606d2c74ae50bd149743d90c3719a164"
}