{
    "AppID": 1951040,
    "Name": "Gangsta Hero",
    "Release date": "Apr 17, 2022",
    "About the game": "notice What you are buying is not the complete finished product of the game, because the visual novel game will be made in a way of continuous update, your purchase will be the biggest support to the author, thank you very much! intro When you graduate you suddenly realized there is a mystery that you broke up with your girlfriend you went to a foreign country alone to seek the truth Sloth city is a city ruled by evil forces, You' re in the middle of a mafia struggle You will meet all kinds of people You can become romeo or remains unspotted from the world, depending on your choice. In an accident, you acquired the ability to change genes Becoming an angel or a demon is just depend on your thoughts Would you be a hero, change this situation or be a villain and enjoy it?",
    "Header image": "https://cdn.akamai.steamstatic.com/steam/apps/1951040/header.jpg?t=1654961491",
    "Price": 9.99,
    "Developers": "HFun Studios",
    "Publishers": "HFun Studios",
    "Screenshots": "https://cdn.akamai.steamstatic.com/steam/apps/1951040/ss_53d6fbff27d32b2f698db561a4dfd7cd0df16645.1920x1080.jpg?t=1654961491,https://cdn.akamai.steamstatic.com/steam/apps/1951040/ss_ccbb164c42e2f37f9a2a68505babd3db62feb26b.1920x1080.jpg?t=1654961491,https://cdn.akamai.steamstatic.com/steam/apps/1951040/ss_9e20a80be6b14bd6bf3c371ab0dc04f3bab55936.1920x1080.jpg?t=1654961491,https://cdn.akamai.steamstatic.com/steam/apps/1951040/ss_7ffb91f45b67bb8d4c13e240a7b16697db8802b4.1920x1080.jpg?t=1654961491,https://cdn.akamai.steamstatic.com/steam/apps/1951040/ss_78f5bb0ce7cff6ac75fec58589a86657dc9dae6c.1920x1080.jpg?t=1654961491,https://cdn.akamai.steamstatic.com/steam/apps/1951040/ss_0b700e0b2dabc76c3f6aea571cc2238477f48be0.1920x1080.jpg?t=1654961491,https://cdn.akamai.steamstatic.com/steam/apps/1951040/ss_7890bdcc86b66ceacfc369076d4ddb394121855f.1920x1080.jpg?t=1654961491,https://cdn.akamai.steamstatic.com/steam/apps/1951040/ss_90e90c255aeb5f08ca4c09a145bb756beb04c02f.1920x1080.jpg?t=1654961491,https://cdn.akamai.steamstatic.com/steam/apps/1951040/ss_efd9fb82d122897ec6c102c0c4499ce5b8fe77cd.1920x1080.jpg?t=1654961491,https://cdn.akamai.steamstatic.com/steam/apps/1951040/ss_b5c5ecc57cb49f53b44e2e6223d28de3f6febb53.1920x1080.jpg?t=1654961491,https://cdn.akamai.steamstatic.com/steam/apps/1951040/ss_bbcae218fcbdab1b0840aaeba8d0ca4694c1f098.1920x1080.jpg?t=1654961491,https://cdn.akamai.steamstatic.com/steam/apps/1951040/ss_37314a9ad072b831a90cec0927523d966cc8a1c3.1920x1080.jpg?t=1654961491,https://cdn.akamai.steamstatic.com/steam/apps/1951040/ss_958a4dc1f633bd3fa19ef6dc98b1ce381bd25012.1920x1080.jpg?t=1654961491,https://cdn.akamai.steamstatic.com/steam/apps/1951040/ss_06dda06ed82eef397d0aac00b339a0c5aac883b7.1920x1080.jpg?t=1654961491,https://cdn.akamai.steamstatic.com/steam/apps/1951040/ss_32a97fcc18fea7c548432a8ed62522c499ddb411.1920x1080.jpg?t=1654961491",
    "Slug": "gangsta-hero",
    "Meta Title": "Gangsta Hero: Apr 17, 2022, HFun Studios and Full Overview",
    "Meta Description": "Looking for information on Gangsta Hero? Check out the release date (Apr 17, 2022), developer insights from HFun Studios, and a complete game summary.",
    "Alt Text Image": "Official header image for Gangsta Hero game - Steam 1951040",
    "Canonical URL": "https://gusku.site/game/gangsta-hero",
    "Schema JSON-LD": "{\"@context\": \"https://schema.org\", \"@type\": \"VideoGame\", \"name\": \"Gangsta Hero\", \"description\": \"Looking for information on Gangsta Hero? Check out the release date (Apr 17, 2022), developer insights from HFun Studios, and a complete game summary.\", \"applicationCategory\": \"Game\", \"operatingSystem\": \"Windows, macOS, Linux\", \"datePublished\": \"Apr 17, 2022\", \"author\": {\"@type\": \"Organization\", \"name\": \"HFun Studios\"}, \"publisher\": {\"@type\": \"Organization\", \"name\": \"HFun Studios\"}, \"image\": \"https://cdn.akamai.steamstatic.com/steam/apps/1951040/header.jpg?t=1654961491\", \"offers\": {\"@type\": \"Offer\", \"price\": 9.99, \"priceCurrency\": \"USD\"}}",
    "img_width": 600,
    "img_height": 900,
    "Link Monetag": "https://otieu.com/4/8764643",
    "Link Adsterra": "https://www.effectivegatecpm.com/xjsgcgii37?key=606d2c74ae50bd149743d90c3719a164"
}