{
    "AppID": 1794690,
    "Name": "Nihongo Heroes",
    "Release date": "Nov 3, 2021",
    "About the game": "'Nihongo Heroes' is an educational game that helps you learn Japanese in a fun way. The Japanese writing system consists of two types of characters: the syllabic kana (hiragana and katakana) and kanji, the adopted Chinese characters. Each have different usages, purposes and characteristics and all are necessary in Japanese writing. This game is using smart learning system that teach Japanese alphabet with vocabularies. While practicing Japanese writing system, you will learn new vocabularies.",
    "Header image": "https://cdn.akamai.steamstatic.com/steam/apps/1794690/header.jpg?t=1635925839",
    "Price": 9.99,
    "Developers": "monacrea",
    "Publishers": "monacrea",
    "Screenshots": "https://cdn.akamai.steamstatic.com/steam/apps/1794690/ss_16ff779eefc93fc0f7d237647fee2a54afa8f33d.1920x1080.jpg?t=1635925839,https://cdn.akamai.steamstatic.com/steam/apps/1794690/ss_d3e5e49050e98315733ef88943dba4b434481f5d.1920x1080.jpg?t=1635925839,https://cdn.akamai.steamstatic.com/steam/apps/1794690/ss_1ef23b25392e98a4edecdb46de8b4602d59498e0.1920x1080.jpg?t=1635925839,https://cdn.akamai.steamstatic.com/steam/apps/1794690/ss_c0339ceb6dc318c87a2d5a7b5da9f732c618e8f3.1920x1080.jpg?t=1635925839,https://cdn.akamai.steamstatic.com/steam/apps/1794690/ss_8a2be69fc0b526ccbba3bc51375ce867007e2967.1920x1080.jpg?t=1635925839,https://cdn.akamai.steamstatic.com/steam/apps/1794690/ss_baca00f7291b9cb6470ab9721d647379463f2922.1920x1080.jpg?t=1635925839,https://cdn.akamai.steamstatic.com/steam/apps/1794690/ss_863176df697b4317c7221d3dccce2c4f64976f19.1920x1080.jpg?t=1635925839,https://cdn.akamai.steamstatic.com/steam/apps/1794690/ss_ca5261b5e4215416cc1bc007a7a543038dd753f0.1920x1080.jpg?t=1635925839,https://cdn.akamai.steamstatic.com/steam/apps/1794690/ss_60d4911a63d9df14da6f00fe7fa2ebc141b91458.1920x1080.jpg?t=1635925839",
    "Slug": "nihongo-heroes",
    "Meta Title": "Nihongo Heroes: Nov 3, 2021, monacrea and Full Overview",
    "Meta Description": "Looking for information on Nihongo Heroes? Check out the release date (Nov 3, 2021), developer insights from monacrea, and a complete game summary.",
    "Alt Text Image": "Official header image for Nihongo Heroes game - Steam 1794690",
    "Canonical URL": "https://gusku.site/game/nihongo-heroes",
    "Schema JSON-LD": "{\"@context\": \"https://schema.org\", \"@type\": \"VideoGame\", \"name\": \"Nihongo Heroes\", \"description\": \"Looking for information on Nihongo Heroes? Check out the release date (Nov 3, 2021), developer insights from monacrea, and a complete game summary.\", \"applicationCategory\": \"Game\", \"operatingSystem\": \"Windows, macOS, Linux\", \"datePublished\": \"Nov 3, 2021\", \"author\": {\"@type\": \"Organization\", \"name\": \"monacrea\"}, \"publisher\": {\"@type\": \"Organization\", \"name\": \"monacrea\"}, \"image\": \"https://cdn.akamai.steamstatic.com/steam/apps/1794690/header.jpg?t=1635925839\", \"offers\": {\"@type\": \"Offer\", \"price\": 9.99, \"priceCurrency\": \"USD\"}}",
    "img_width": 600,
    "img_height": 900,
    "Link Monetag": "https://otieu.com/4/8764643",
    "Link Adsterra": "https://www.effectivegatecpm.com/xjsgcgii37?key=606d2c74ae50bd149743d90c3719a164"
}