{
    "AppID": 1360080,
    "Name": "Space Battle Arena",
    "Release date": "Aug 19, 2020",
    "About the game": "Space fight arena is a retro arcade based arena shooter game that was modeled after legendary arcade games. This game retains the fun, addicting aspects of those arcade games while also adding on new, awesome features such as challenges, skins, and a world wide leaderboard. Play and complete all the challenges, unlock all of the skins, and climb to the very top of the leaderboard. Space Fight Arena has so much to offer and the best part is that more and more content will continue to be added weekly!",
    "Header image": "https://cdn.akamai.steamstatic.com/steam/apps/1360080/header.jpg?t=1597859250",
    "Price": 2.99,
    "Developers": "Sam Ghalili",
    "Publishers": "Sam Ghalili",
    "Screenshots": "https://cdn.akamai.steamstatic.com/steam/apps/1360080/ss_c9e2653cbde4757f1130a611ad40d20aca552a68.1920x1080.jpg?t=1597859250,https://cdn.akamai.steamstatic.com/steam/apps/1360080/ss_a417e1e98d98a826401f2b9c0714da748600303f.1920x1080.jpg?t=1597859250,https://cdn.akamai.steamstatic.com/steam/apps/1360080/ss_2b7e8b69f924d19595af4ad667e0c044760f8dcd.1920x1080.jpg?t=1597859250,https://cdn.akamai.steamstatic.com/steam/apps/1360080/ss_b375fd49a0d67ce7cf3b5160d0b2fd407869d735.1920x1080.jpg?t=1597859250,https://cdn.akamai.steamstatic.com/steam/apps/1360080/ss_027962fa37ce2ddf6fd6c7fcfc606995ed60a6ce.1920x1080.jpg?t=1597859250",
    "Slug": "space-battle-arena",
    "Meta Title": "Space Battle Arena: Aug 19, 2020, Sam Ghalili and Full Ov...",
    "Meta Description": "Looking for information on Space Battle Arena? Check out the release date (Aug 19, 2020), developer insights from Sam Ghalili, and a complete game summary.",
    "Alt Text Image": "Official header image for Space Battle Arena game - Steam 1360080",
    "Canonical URL": "https://gusku.site/game/space-battle-arena",
    "Schema JSON-LD": "{\"@context\": \"https://schema.org\", \"@type\": \"VideoGame\", \"name\": \"Space Battle Arena\", \"description\": \"Looking for information on Space Battle Arena? Check out the release date (Aug 19, 2020), developer insights from Sam Ghalili, and a complete game summary.\", \"applicationCategory\": \"Game\", \"operatingSystem\": \"Windows, macOS, Linux\", \"datePublished\": \"Aug 19, 2020\", \"author\": {\"@type\": \"Organization\", \"name\": \"Sam Ghalili\"}, \"publisher\": {\"@type\": \"Organization\", \"name\": \"Sam Ghalili\"}, \"image\": \"https://cdn.akamai.steamstatic.com/steam/apps/1360080/header.jpg?t=1597859250\", \"offers\": {\"@type\": \"Offer\", \"price\": 2.99, \"priceCurrency\": \"USD\"}}",
    "img_width": 600,
    "img_height": 900,
    "Link Monetag": "https://otieu.com/4/8764643",
    "Link Adsterra": "https://www.effectivegatecpm.com/xjsgcgii37?key=606d2c74ae50bd149743d90c3719a164"
}