[
  {
    "title": "Wuthering Heights",
    "poster": "https://image.tmdb.org/t/p/w500/6V4sA6F7kT72IdZx1U2ujb4YXmb.jpg",
    "director": "Peter Kosminsky",
    "movie_id": "25095",
    "release_date": "1992-10-16",
    "runtime": "105",
    "overview": "Young orphan Heathcliff is adopted by the wealthy Earnshaw family and moves into their estate, Wuthering Heights. Soon, the new resident falls for his compassionate foster sister, Cathy. The two share a remarkable bond that seems unbreakable until Cathy, feeling the pressure of social convention, suppresses her feelings and marries Edgar Linton, a man of means who befits her stature. Heathcliff vows to win her back."
  }
]