[
  {
    "title": "Oblivium",
    "poster": "https://image.tmdb.org/t/p/w500/12Cm2NUChrzrW5HxpABLFtCg0Au.jpg",
    "director": "Ibrahim Ashmawey",
    "movie_id": "1508090",
    "release_date": "2025-07-08",
    "runtime": "92",
    "overview": "Sky just wanted to avoid her estranged grandmother with Alzheimer’s—but when she finally visits, she uncovers a haunting mystery. Surrounded by ghostly figures that vanish from memory the moment they’re unseen, Sky and her friends find themselves trapped in a terrifying cycle of forgotten horrors."
  }
]