[
  {
    "title": "Varg Veum - Cold Hearts",
    "poster": "https://image.tmdb.org/t/p/w500/1bqzUEZ9dZqbUT7GM4wpBx3F629.jpg",
    "director": "Trond Espen Seim",
    "movie_id": "111426",
    "release_date": "2012-03-30",
    "runtime": "90",
    "overview": "Varg Veum is going to be a father. In a way he could never imagine, life takes on a new direction while he is searching for a missing pair of siblings in the prostitution circles in Bergen. Varg realizes that life will never be the same when he has to make a decision: Let the criminals go free or expose Karin to mortal danger."
  }
]