[
  {
    "title": "Meeting People Is Easy",
    "poster": "https://image.tmdb.org/t/p/w500/3WtnnmgQNAZ2il10aW86haQI8g1.jpg",
    "director": "Grant Gee",
    "movie_id": "19362",
    "release_date": "1998-03-20",
    "runtime": "95",
    "overview": "Meeting People Is Easy takes place during the promotion of Radiohead's 1997 release OK Computer, containing a collage of video clips, sound bites, and dialogue going behind the scenes with the band on their world tour, showing the eventual burn-out of the group as the world tour progresses. The inaugural show of the OK Computer tour began on 22 May 1997 in Barcelona, Spain."
  }
]