[
  {
    "title": "Scarecrows",
    "poster": "https://image.tmdb.org/t/p/w500/xaUdO29mwujiz2NcicSAk4u1NIJ.jpg",
    "director": "William Wesley",
    "movie_id": "40168",
    "release_date": "1988-09-28",
    "runtime": "83",
    "overview": "Five men heist the Camp Pendleton payroll and kidnap a pilot and his daughter, who are forced to fly them to Mexico. Enroute a double cross has one of the thieves parachute with the loot into an abandoned farm surrounded by strange scarecrows. The rest of the team jump after their loot and their former partner. Everything happens during the course of one very dark night."
  }
]