[
  {
    "title": "The Disappearance of My Mother",
    "poster": "https://image.tmdb.org/t/p/w500/kxT7JuffE0FKw2xc9zBPDAnMuZG.jpg",
    "director": "Beniamino Barrese",
    "movie_id": "566062",
    "release_date": "2019-10-10",
    "runtime": "94",
    "overview": "Aging fashion model Benedetta Barzini strives to escape the world of images and disappear for good, but her son’s determination to make a final film about her sparks an unexpected collaboration and confrontation with the camera’s gaze."
  }
]