[
  {
    "title": "The Edge",
    "poster": "https://image.tmdb.org/t/p/w500/c5uLlEp9ZX0HlRXkFr8UPEweuMt.jpg",
    "director": "Robert Kramer",
    "movie_id": "262755",
    "release_date": "1968-03-26",
    "runtime": "100",
    "overview": "A troubled antiwar activist plans to assassinate the President of the United States. His resolve forces others in a fragmented and disillusioned group of political allies to face the threat of government counterintelligence and the temptations of middle-age security, and to reexamine their commitment to radical action."
  }
]