[
  {
    "title": "For Love or Money",
    "poster": "https://image.tmdb.org/t/p/w500/d3LkvenB5NAAVnqfwIxkhCfdkNa.jpg",
    "director": "Barry Sonnenfeld",
    "movie_id": "9024",
    "release_date": "1993-10-01",
    "runtime": "94",
    "overview": "New York concierge Doug Ireland wants to go into business for himself and refurbish a hotel on Roosevelt Island, N.Y., but he needs an investor. With a few weeks left before his option on the site runs out, Doug agrees to help wealthy Christian Hanover conceal his affair with salesgirl Andy Hart from his wife. Despite his own attraction to Andy, Doug tries to stay focused on getting Christian to invest $3 million in his project."
  }
]