[
  {
    "title": "The Hutong Cowboy",
    "poster": "https://image.tmdb.org/t/p/w500/rwMjHwItj3Dl4iJuGzvuY0bRrLo.jpg",
    "director": "Ning Hao",
    "movie_id": "1197437",
    "release_date": "2024-10-01",
    "runtime": "0",
    "overview": "Zhang Beijing loss his face at his son’s engagement party. After that he refunds the sense of purpose by helping Liu Angxi, a screenwriter of the Beidiao Neighbour's talk show. However, he was pushed into the limelight after being used as material by Liu Angxi, and their friendship broke down"
  }
]