[
  {
    "title": "The Farm",
    "poster": "https://image.tmdb.org/t/p/w500/7nPMR3QU5vl7cEmB1LE6O6yliCg.jpg",
    "director": "Hans Stjernswärd",
    "movie_id": "517764",
    "release_date": "2019-04-19",
    "runtime": "80",
    "overview": "The young couple Nora and Alec are on their way back from a long road trip. In a  desert town they want to take a break, but when they wake up the next morning, they are no longer in the motel where they had actually checked in. Overnight, the by a group of crazed killers wearing animal masks, have been abducted.  What would happen if people were treated like cattle for slaughter? On the farm, this horrific idea comes true. As Nora and Alec soon find out, they are not the only ones locked in cages, fattened up and fed only to be slaughtered, disemboweled and eaten as a delicacy by their torturers. For the young couple begins a fight for bare survival."
  }
]