[
  {
    "title": "The Charge of the Light Brigade",
    "poster": "https://image.tmdb.org/t/p/w500/v7PFjyhEAWKGQ8g6cTGw4GzYKsa.jpg",
    "director": "Michael Curtiz",
    "movie_id": "43884",
    "release_date": "1936-10-20",
    "runtime": "111",
    "overview": "In 1853, as the British and Russian empires compete to gain and maintain their place in the dreadful Great Game of political intrigues and alliances whose greatest prize is the domination of India and the border territories, Major Geoffrey Vickers must endure several betrayals and misfortunes before he can achieve his revenge at the Balaclava Heights, on October 25, 1854, the most glorious day of the Crimean War."
  }
]