{
    "AppID": 656210,
    "Name": "ROMBY",
    "Release date": "Jul 26, 2017",
    "About the game": "In ROMBY you will earn points by placing 4 and even more figures of one color in a straight line. Earn more points and open all hidden girls. Trust me it won't be easy. - Every round is unique - Fast and fun gameplay - Great soundtrack - Global rating and achievements - Lots of missions - Girls",
    "Header image": "https://cdn.akamai.steamstatic.com/steam/apps/656210/header.jpg?t=1524113821",
    "Price": 0.99,
    "Developers": "Black Lime Studio",
    "Publishers": "Black Lime Studio",
    "Screenshots": "https://cdn.akamai.steamstatic.com/steam/apps/656210/ss_ed70fe6fff7bbf10c6f9216aacfa9e5758956972.1920x1080.jpg?t=1524113821,https://cdn.akamai.steamstatic.com/steam/apps/656210/ss_5a00aec7bb0ef59a09b66a85064aa72ea3bcaa00.1920x1080.jpg?t=1524113821,https://cdn.akamai.steamstatic.com/steam/apps/656210/ss_ac62e54b22a7fe204a373f84c9f962cfc0f696ac.1920x1080.jpg?t=1524113821,https://cdn.akamai.steamstatic.com/steam/apps/656210/ss_430838e5ed9d8727fc08bf873bdab7bc09d2a258.1920x1080.jpg?t=1524113821,https://cdn.akamai.steamstatic.com/steam/apps/656210/ss_77f151c1031b29155e40dec0de2837e6e905f3af.1920x1080.jpg?t=1524113821,https://cdn.akamai.steamstatic.com/steam/apps/656210/ss_b52189b95bb5e3cb9e3b249745a4c5b90e8f44d1.1920x1080.jpg?t=1524113821,https://cdn.akamai.steamstatic.com/steam/apps/656210/ss_420c08c6eb23b02b5122487a16a437c5b30d4829.1920x1080.jpg?t=1524113821,https://cdn.akamai.steamstatic.com/steam/apps/656210/ss_35808eb5a600cb86a67598b5fed91967117af744.1920x1080.jpg?t=1524113821",
    "Slug": "romby",
    "Meta Title": "ROMBY: Jul 26, 2017, Black Lime Studio and Full Overview",
    "Meta Description": "Looking for information on ROMBY? Check out the release date (Jul 26, 2017), developer insights from Black Lime Studio, and a complete game summary.",
    "Alt Text Image": "Official header image for ROMBY game - Steam 656210",
    "Canonical URL": "https://gusku.site/game/romby",
    "Schema JSON-LD": "{\"@context\": \"https://schema.org\", \"@type\": \"VideoGame\", \"name\": \"ROMBY\", \"description\": \"Looking for information on ROMBY? Check out the release date (Jul 26, 2017), developer insights from Black Lime Studio, and a complete game summary.\", \"applicationCategory\": \"Game\", \"operatingSystem\": \"Windows, macOS, Linux\", \"datePublished\": \"Jul 26, 2017\", \"author\": {\"@type\": \"Organization\", \"name\": \"Black Lime Studio\"}, \"publisher\": {\"@type\": \"Organization\", \"name\": \"Black Lime Studio\"}, \"image\": \"https://cdn.akamai.steamstatic.com/steam/apps/656210/header.jpg?t=1524113821\", \"offers\": {\"@type\": \"Offer\", \"price\": 0.99, \"priceCurrency\": \"USD\"}}",
    "img_width": 600,
    "img_height": 900,
    "Link Monetag": "https://otieu.com/4/8764643",
    "Link Adsterra": "https://www.effectivegatecpm.com/xjsgcgii37?key=606d2c74ae50bd149743d90c3719a164"
}