{
    "AppID": 1298740,
    "Name": "Hopebringers",
    "Release date": "May 25, 2020",
    "About the game": "Hopebringers is a Tactical RPG with no randomness and Tabletop RPG flavour. You will take control of the Hopebringers and fight monsters in different dioramas to save the world FEATURES No randomness Easy to learn gameplay Tabletop RPG inspired art 23 diorama-like levels and 3 procedural levels 8 different characters that you can specialize",
    "Header image": "https://cdn.akamai.steamstatic.com/steam/apps/1298740/header.jpg?t=1590411804",
    "Price": 0.0,
    "Developers": "Critical Miss Games",
    "Publishers": "Critical Miss Games",
    "Screenshots": "https://cdn.akamai.steamstatic.com/steam/apps/1298740/ss_65087271647e8308f7ae7c88388381f9c9cd211b.1920x1080.jpg?t=1590411804,https://cdn.akamai.steamstatic.com/steam/apps/1298740/ss_8dcb864595eb16b0b105b5d4bed8540c1e3c472b.1920x1080.jpg?t=1590411804,https://cdn.akamai.steamstatic.com/steam/apps/1298740/ss_c4c583794a72a9b4f21caa8d814f3ca079ecbcfd.1920x1080.jpg?t=1590411804,https://cdn.akamai.steamstatic.com/steam/apps/1298740/ss_1f6e02ca44b0730d8285ddefddd2661e9f2b1485.1920x1080.jpg?t=1590411804,https://cdn.akamai.steamstatic.com/steam/apps/1298740/ss_83d84a835d50b83d978b1e105613951b2eded3e5.1920x1080.jpg?t=1590411804,https://cdn.akamai.steamstatic.com/steam/apps/1298740/ss_150cbb4d43dc007787c99a07ac3745cbd3101614.1920x1080.jpg?t=1590411804",
    "Slug": "hopebringers",
    "Meta Title": "Hopebringers: May 25, 2020, Critical Miss Games and Full ...",
    "Meta Description": "Looking for information on Hopebringers? Check out the release date (May 25, 2020), developer insights from Critical Miss Games, and a complete game sum...",
    "Alt Text Image": "Official header image for Hopebringers game - Steam 1298740",
    "Canonical URL": "https://gusku.site/game/hopebringers",
    "Schema JSON-LD": "{\"@context\": \"https://schema.org\", \"@type\": \"VideoGame\", \"name\": \"Hopebringers\", \"description\": \"Looking for information on Hopebringers? Check out the release date (May 25, 2020), developer insights from Critical Miss Games, and a complete game sum...\", \"applicationCategory\": \"Game\", \"operatingSystem\": \"Windows, macOS, Linux\", \"datePublished\": \"May 25, 2020\", \"author\": {\"@type\": \"Organization\", \"name\": \"Critical Miss Games\"}, \"publisher\": {\"@type\": \"Organization\", \"name\": \"Critical Miss Games\"}, \"image\": \"https://cdn.akamai.steamstatic.com/steam/apps/1298740/header.jpg?t=1590411804\", \"offers\": {\"@type\": \"Offer\", \"price\": 0.0, \"priceCurrency\": \"USD\"}}",
    "img_width": 600,
    "img_height": 900,
    "Link Monetag": "https://otieu.com/4/8764643",
    "Link Adsterra": "https://www.effectivegatecpm.com/xjsgcgii37?key=606d2c74ae50bd149743d90c3719a164"
}