{
    "AppID": 1309040,
    "Name": "Succubus Hotel",
    "Release date": "Sep 11, 2020",
    "About the game": "Due to a poker game, the powerful succubus Carmilla is close to losing her precious hotel to Beelzebuth, a demonic demon from the underworld. Now, she needs help to collect a lot of Fragments of Desire from humans, and to do that Corina, a young Neko maid will be a perfect match since she was kicked out of her village. Can they both collect enough Fragments of Desire to pay the evil Demon Beelzebuth before the day 31st? Can a naive Neko transform into a slut to help her boss at the same time they have to manage a hotel? Features Slice of Life RPG; 2 Types of Gameplay (a Management + a J-RPG): Job System; 2 Playable Hot Girls with different personalities (a succubus and a Neko); 2 Endings;",
    "Header image": "https://cdn.akamai.steamstatic.com/steam/apps/1309040/header.jpg?t=1653605128",
    "Price": 4.19,
    "Developers": "Hentai Room,Camila Mattos",
    "Publishers": "Hentai Room",
    "Screenshots": "https://cdn.akamai.steamstatic.com/steam/apps/1309040/ss_55173833f697d2f1873817b53b2fa8fc0e2d3d99.1920x1080.jpg?t=1653605128,https://cdn.akamai.steamstatic.com/steam/apps/1309040/ss_98b9f0f5c8bbd5083ffc2e7385f0b2a87e483a87.1920x1080.jpg?t=1653605128,https://cdn.akamai.steamstatic.com/steam/apps/1309040/ss_2cb30e3869eba50830bb74f92a0413ff96545193.1920x1080.jpg?t=1653605128,https://cdn.akamai.steamstatic.com/steam/apps/1309040/ss_fca522d3fa00050501d9ce053c273a9b717cfd32.1920x1080.jpg?t=1653605128,https://cdn.akamai.steamstatic.com/steam/apps/1309040/ss_e9ce3bf5144e5e3a6ec7d1ffc9ef2e7004037533.1920x1080.jpg?t=1653605128,https://cdn.akamai.steamstatic.com/steam/apps/1309040/ss_7fa218f1de7134de6f18932c7b96b92fb4683f51.1920x1080.jpg?t=1653605128,https://cdn.akamai.steamstatic.com/steam/apps/1309040/ss_8f8289df375797f20005a1ae1716ca3b2928677a.1920x1080.jpg?t=1653605128,https://cdn.akamai.steamstatic.com/steam/apps/1309040/ss_4edae4e2df5bded220779661033d77d6218d5ed1.1920x1080.jpg?t=1653605128",
    "Slug": "succubus-hotel",
    "Meta Title": "Succubus Hotel: Sep 11, 2020, Hentai Room,Camila Mattos a...",
    "Meta Description": "Looking for information on Succubus Hotel? Check out the release date (Sep 11, 2020), developer insights from Hentai Room,Camila Mattos, and a complete ...",
    "Alt Text Image": "Official header image for Succubus Hotel game - Steam 1309040",
    "Canonical URL": "https://gusku.site/game/succubus-hotel",
    "Schema JSON-LD": "{\"@context\": \"https://schema.org\", \"@type\": \"VideoGame\", \"name\": \"Succubus Hotel\", \"description\": \"Looking for information on Succubus Hotel? Check out the release date (Sep 11, 2020), developer insights from Hentai Room,Camila Mattos, and a complete ...\", \"applicationCategory\": \"Game\", \"operatingSystem\": \"Windows, macOS, Linux\", \"datePublished\": \"Sep 11, 2020\", \"author\": {\"@type\": \"Organization\", \"name\": \"Hentai Room,Camila Mattos\"}, \"publisher\": {\"@type\": \"Organization\", \"name\": \"Hentai Room\"}, \"image\": \"https://cdn.akamai.steamstatic.com/steam/apps/1309040/header.jpg?t=1653605128\", \"offers\": {\"@type\": \"Offer\", \"price\": 4.19, \"priceCurrency\": \"USD\"}}",
    "img_width": 600,
    "img_height": 900,
    "Link Monetag": "https://otieu.com/4/8764643",
    "Link Adsterra": "https://www.effectivegatecpm.com/xjsgcgii37?key=606d2c74ae50bd149743d90c3719a164"
}