{
    "AppID": 1390860,
    "Name": "Re: Award",
    "Release date": "May 31, 2021",
    "About the game": "Third person Corridor Walking Simulator. A game of searching for objects using a special ability. Story Rin's friend Scarlett came to Rin's grandfather's house in the country. Rin's grandfather died when she was young, and Rin wants to know what kind of person her grandfather was. Scarlett's special ability Scarlett has a special ability to project what was there in the past. She can project the old furnitures of Rin's grandfather. If you can project all the furniture, the game will be completed. Operations Viewpoint changes: Moving mouse Walk: W, A, S, D Use a special ability: Hold the right mouse button Pause screen: ESC key Xbox controller Viewpoint changes: Right stick Walk: Left stick Use a special ability: LB",
    "Header image": "https://cdn.akamai.steamstatic.com/steam/apps/1390860/header.jpg?t=1641814446",
    "Price": 0.0,
    "Developers": "Sonic-Alpha",
    "Publishers": "Sonic-Beta",
    "Screenshots": "https://cdn.akamai.steamstatic.com/steam/apps/1390860/ss_055e19bc8581c00a7bf77c866a1f4a099f755d5f.1920x1080.jpg?t=1641814446,https://cdn.akamai.steamstatic.com/steam/apps/1390860/ss_8c8e99e37c04d86b6f84b345ee2bc90ff2503463.1920x1080.jpg?t=1641814446,https://cdn.akamai.steamstatic.com/steam/apps/1390860/ss_fdc64ca1c2e78a24ca7b959b452688777c2eaf3f.1920x1080.jpg?t=1641814446,https://cdn.akamai.steamstatic.com/steam/apps/1390860/ss_8722a2398f8d2714b0f2630659e011349b895480.1920x1080.jpg?t=1641814446,https://cdn.akamai.steamstatic.com/steam/apps/1390860/ss_af029fd4594a3fc75aa39eb329af8ed3eb6d9bf0.1920x1080.jpg?t=1641814446,https://cdn.akamai.steamstatic.com/steam/apps/1390860/ss_e6353d36b851a67385bda439d11955a4ea4d1577.1920x1080.jpg?t=1641814446,https://cdn.akamai.steamstatic.com/steam/apps/1390860/ss_ae8031dfef8c9e54ede07e5ce42cc1afce4f46f2.1920x1080.jpg?t=1641814446",
    "Slug": "re-award",
    "Meta Title": "Re: Award: May 31, 2021, Sonic-Alpha and Full Overview",
    "Meta Description": "Looking for information on Re: Award? Check out the release date (May 31, 2021), developer insights from Sonic-Alpha, and a complete game summary.",
    "Alt Text Image": "Official header image for Re: Award game - Steam 1390860",
    "Canonical URL": "https://gusku.site/game/re-award",
    "Schema JSON-LD": "{\"@context\": \"https://schema.org\", \"@type\": \"VideoGame\", \"name\": \"Re: Award\", \"description\": \"Looking for information on Re: Award? Check out the release date (May 31, 2021), developer insights from Sonic-Alpha, and a complete game summary.\", \"applicationCategory\": \"Game\", \"operatingSystem\": \"Windows, macOS, Linux\", \"datePublished\": \"May 31, 2021\", \"author\": {\"@type\": \"Organization\", \"name\": \"Sonic-Alpha\"}, \"publisher\": {\"@type\": \"Organization\", \"name\": \"Sonic-Beta\"}, \"image\": \"https://cdn.akamai.steamstatic.com/steam/apps/1390860/header.jpg?t=1641814446\", \"offers\": {\"@type\": \"Offer\", \"price\": 0.0, \"priceCurrency\": \"USD\"}}",
    "img_width": 600,
    "img_height": 900,
    "Link Monetag": "https://otieu.com/4/8764643",
    "Link Adsterra": "https://www.effectivegatecpm.com/xjsgcgii37?key=606d2c74ae50bd149743d90c3719a164"
}