{
    "AppID": 1069520,
    "Name": "Green Field Silver Tree / 绿野白银树",
    "Release date": "May 9, 2019",
    "About the game": "You are an ordinary high school student, but you have gained spiritual power in one incident. The person who gives you the power to tell you that you must exercise yourself to defeat God. Different Worlds You will experience the ordinary world and the world full of spirituality, and even the world after death. New Beginning After you have a little strength, you start a new adventure. You will resolve the conflict between the two schools. You will recognize the true face of a gaming company. You will also commit suicide to save your friends. Simple Battle You only have two common combos, a normal spiritual attack, and a plain skill. However, your enemies will use a wealth of skills, you must make good use of dodge and defense",
    "Header image": "https://cdn.akamai.steamstatic.com/steam/apps/1069520/header.jpg?t=1557442476",
    "Price": 4.99,
    "Developers": "超镦逸",
    "Publishers": "超镦逸",
    "Screenshots": "https://cdn.akamai.steamstatic.com/steam/apps/1069520/ss_511f41aa03b2e1baa6ddbc599506638ed1606a30.1920x1080.jpg?t=1557442476,https://cdn.akamai.steamstatic.com/steam/apps/1069520/ss_a7a73a875de602bd35d39c8cc733e26b9fe5b0ab.1920x1080.jpg?t=1557442476,https://cdn.akamai.steamstatic.com/steam/apps/1069520/ss_e0b630c3a0624975a843a28e83ee612e1fa45cf4.1920x1080.jpg?t=1557442476,https://cdn.akamai.steamstatic.com/steam/apps/1069520/ss_016bde7a11089fcb942278957f55a167f5e97fa0.1920x1080.jpg?t=1557442476,https://cdn.akamai.steamstatic.com/steam/apps/1069520/ss_29f692ee3b392bfe7b2f66db36f65e2d73666a99.1920x1080.jpg?t=1557442476",
    "Slug": "green-field-silver-tree",
    "Meta Title": "Green Field Silver Tree / 绿野白银树: May 9, 2019, 超镦逸 and Ful...",
    "Meta Description": "Looking for information on Green Field Silver Tree / 绿野白银树? Check out the release date (May 9, 2019), developer insights from 超镦逸, and a complete game s...",
    "Alt Text Image": "Official header image for Green Field Silver Tree / 绿野白银树 game - Steam 1069520",
    "Canonical URL": "https://gusku.site/game/green-field-silver-tree",
    "Schema JSON-LD": "{\"@context\": \"https://schema.org\", \"@type\": \"VideoGame\", \"name\": \"Green Field Silver Tree / \\u7eff\\u91ce\\u767d\\u94f6\\u6811\", \"description\": \"Looking for information on Green Field Silver Tree / \\u7eff\\u91ce\\u767d\\u94f6\\u6811? Check out the release date (May 9, 2019), developer insights from \\u8d85\\u9566\\u9038, and a complete game s...\", \"applicationCategory\": \"Game\", \"operatingSystem\": \"Windows, macOS, Linux\", \"datePublished\": \"May 9, 2019\", \"author\": {\"@type\": \"Organization\", \"name\": \"\\u8d85\\u9566\\u9038\"}, \"publisher\": {\"@type\": \"Organization\", \"name\": \"\\u8d85\\u9566\\u9038\"}, \"image\": \"https://cdn.akamai.steamstatic.com/steam/apps/1069520/header.jpg?t=1557442476\", \"offers\": {\"@type\": \"Offer\", \"price\": 4.99, \"priceCurrency\": \"USD\"}}",
    "img_width": 600,
    "img_height": 900,
    "Link Monetag": "https://otieu.com/4/8764643",
    "Link Adsterra": "https://www.effectivegatecpm.com/xjsgcgii37?key=606d2c74ae50bd149743d90c3719a164"
}